leohs/__init__.py
leohs/io.py
leohs/main.py
leohs/points.py
leohs/regression.py
leohs/sampling.py
leohs/wrs.py
leohs/data/WRS_overlaps.cpg
leohs/data/WRS_overlaps.dbf
leohs/data/WRS_overlaps.prj
leohs/data/WRS_overlaps.shp
leohs/data/WRS_overlaps.shx
leohs-1.1.0.dist-info/licenses/LICENSE
leohs-1.1.0.dist-info/METADATA
leohs-1.1.0.dist-info/WHEEL
leohs-1.1.0.dist-info/entry_points.txt
leohs-1.1.0.dist-info/top_level.txt
leohs-1.1.0.dist-info/RECORD
