Metadata-Version: 2.4
Name: leohs
Version: 1.1.0
Summary: Landsat ETM+ OLI Harmonization Script
Author-email: Galen Richardson <galenrichardsonam@gmail.com>
License: Copyright (C) 2025 Galen Richardson
Classifier: Intended Audience :: Science/Research
Classifier: Topic :: Scientific/Engineering :: GIS
Classifier: License :: OSI Approved :: GNU General Public License v3 or later (GPLv3+)
Classifier: Programming Language :: Python :: 3.10
Classifier: Operating System :: OS Independent
Requires-Python: <3.11,>=3.10
License-File: LICENSE
Requires-Dist: geopandas==0.14.0
Requires-Dist: shapely==2.0.1
Requires-Dist: rasterio==1.3.8
Requires-Dist: geopy==2.4.1
Requires-Dist: numpy==1.24.3
Requires-Dist: pandas==2.1.1
Requires-Dist: fiona==1.9.4
Requires-Dist: matplotlib==3.8.0
Requires-Dist: scikit-learn==1.3.1
Requires-Dist: joblib==1.3.2
Requires-Dist: earthengine-api==0.1.404
Requires-Dist: geemap==0.32.0
Requires-Dist: xgboost==2.0.0
Dynamic: license-file
